singleton_classes/__init__.py
singleton_classes/singleton.py
singleton_classes/singleton_by_class.py
singleton_classes/singleton_by_class_and_id.py
singleton_classes/exceptions/__init__.py
singleton_classes/exceptions/base_singleton_exception.py
singleton_classes/exceptions/singleton_by_class_and_id_exception.py
singleton_classes/exceptions/singleton_by_class_exception.py
singleton_classes/exceptions/singleton_exception.py
singleton_classes-1.0.dist-info/METADATA
singleton_classes-1.0.dist-info/WHEEL
singleton_classes-1.0.dist-info/top_level.txt
singleton_classes-1.0.dist-info/RECORD
