Metadata-Version: 2.1
Name: singleton-classes
Version: 1.0
Summary: package for different Singleton classes and metaclasses
Author: Marc MALBERT
Author-email: eldrad-59@hotmail.fr
Classifier: Programming Language :: Python :: 3
Classifier: Development Status :: 5 - Production/Stable
Classifier: Natural Language :: English
Classifier: Operating System :: OS Independent
